dls_backup_bl/VERSION
dls_backup_bl/__init__.py
dls_backup_bl/__main__.py
dls_backup_bl/_version.py
dls_backup_bl/backup.py
dls_backup_bl/brick.py
dls_backup_bl/config.py
dls_backup_bl/config_schema.json
dls_backup_bl/defaults.py
dls_backup_bl/importjson.py
dls_backup_bl/repository.py
dls_backup_bl/tserver.py
dls_backup_bl/zebra.py
dls_backup_bl/global_git_config/.gitconfig
dls_backup_bl-1.2.2.dist-info/licenses/LICENSE
dls_backup_gui/__init__.py
dls_backup_gui/backupeditor.py
dls_backup_gui/dls_backup_gui.py
dls_backup_gui/entries.py
dls_backup_bl-1.2.2.dist-info/METADATA
dls_backup_bl-1.2.2.dist-info/WHEEL
dls_backup_bl-1.2.2.dist-info/entry_points.txt
dls_backup_bl-1.2.2.dist-info/top_level.txt
dls_backup_bl-1.2.2.dist-info/RECORD
