Metadata-Version: 2.4
Name: dls-backup-bl
Version: 1.2.2
Summary: A backup tool for beamlines for pmacs, terminal servers, zebras
Author-email: James OHea <James.OHea@diamond.ac.uk>
License:                                  Apache License
Project-URL: GitHub, https://github.com/DiamondLightSource/dls-backup-bl
Classifier: Development Status :: 3 - Alpha
Classifier: License :: OSI Approved :: Apache Software License
Classifier: Programming Language :: Python :: 3.11
Classifier: Programming Language :: Python :: 3.12
Requires-Python: >=3.11
License-File: LICENSE
Requires-Dist: attrs>=19.1.0
Requires-Dist: cothread
Requires-Dist: dls-pmacanalyse>=3.0.0
Requires-Dist: epicscorelibs
Requires-Dist: gitpython
Requires-Dist: numpy
Requires-Dist: pyqt5
Requires-Dist: pexpect
Requires-Dist: requests
Requires-Dist: urllib3==1.26.20
Provides-Extra: dev
Requires-Dist: copier; extra == "dev"
Requires-Dist: mypy; extra == "dev"
Requires-Dist: pipdeptree; extra == "dev"
Requires-Dist: pre-commit; extra == "dev"
Requires-Dist: pytest; extra == "dev"
Requires-Dist: pytest-cov; extra == "dev"
Requires-Dist: types-requests; extra == "dev"
Requires-Dist: ruff; extra == "dev"
Requires-Dist: tox-direct; extra == "dev"
Requires-Dist: types-mock; extra == "dev"
Dynamic: license-file
